__init__.py
__main__.py
server.py
pixabay_mcp-1.0.0.dist-info/METADATA
pixabay_mcp-1.0.0.dist-info/WHEEL
pixabay_mcp-1.0.0.dist-info/entry_points.txt
pixabay_mcp-1.0.0.dist-info/top_level.txt
pixabay_mcp-1.0.0.dist-info/RECORD
